funkybox-0.1.11.dist-info/METADATA
funkybox-0.1.11.dist-info/WHEEL
funkybox.cp38-win_amd64.pyd
funkybox-0.1.11.dist-info/RECORD
