Metadata-Version: 2.1
Name: funkybox
Version: 0.1.11
Summary: A collection of utility python functions made in rust.
Keywords: python utility utilities
Author: Paul Amazona
License: MIT
